terrafai/__init__.py
terrafai/main.tf
terrafai/terrafai.py
terrafai/tfai_output_20241007_10.48.08/main.tf
terrafai-0.1.7.dist-info/METADATA
terrafai-0.1.7.dist-info/WHEEL
terrafai-0.1.7.dist-info/entry_points.txt
terrafai-0.1.7.dist-info/licenses/LICENSE
terrafai-0.1.7.dist-info/RECORD
