Metadata-Version: 2.3
Name: terrafai
Version: 0.1.7
Summary: Apply OpenAI gpt changes to an entire Terraform project directory
Project-URL: Homepage, https://github.com/jacobm3/terrafai
Project-URL: Bug Tracker, https://github.com/jacobm3/terrafai/issues
Author-email: Jacob Mthree <jacobm3@gmail.com>
License-File: LICENSE
Classifier: License :: OSI Approved :: GNU General Public License v3 or later (GPLv3+)
Classifier: Operating System :: OS Independent
Classifier: Programming Language :: Python :: 3
Requires-Python: >=3.7
Requires-Dist: langchain==0.0.190
Requires-Dist: openai==0.28
Requires-Dist: python-dotenv
Requires-Dist: python-hcl2
